surquest/GCP/secret_assessor/__init__.py
surquest/GCP/secret_assessor/exceptions.py
surquest/GCP/secret_assessor/secret.py
surquest_gcp_secret_assessor-0.0.4.dist-info/METADATA
surquest_gcp_secret_assessor-0.0.4.dist-info/WHEEL
surquest_gcp_secret_assessor-0.0.4.dist-info/licenses/LICENSE
surquest_gcp_secret_assessor-0.0.4.dist-info/RECORD
