Metadata-Version: 2.1
Name: surquest-GCP-secret-assessor
Version: 0.0.4
Summary: Utility package for assessing Google Cloud Platform (GCP) secrets uniformly
Project-URL: Homepage, https://github.com/surquest/python-gcp-secrets-assessor
Project-URL: Bug Tracker, https://github.com/surquest/python-gcp-secrets-assessor/issues
Author-email: Michal Švarc <michal.svarc@surquest.com>
License-Expression: MIT
License-File: LICENSE
Classifier: License :: OSI Approved :: MIT License
Classifier: Programming Language :: Python :: 3
Requires-Dist: google-auth<3.0.0,>=2.10.0
Requires-Dist: google-cloud-secret-manager<3.0.0,>=2.10.0
Requires-Dist: pyyaml>=6.0
Provides-Extra: test
Requires-Dist: pytest-cov>=4.0.0; extra == 'test'
Requires-Dist: pytest>=7.2.1; extra == 'test'
